<?xml version="1.0" encoding="UTF-8"?>
<objects serializationModel="Studio.02.03.00">
	<object class="Event" id="{c62818e9-c627-477f-91e7-ade3af931cc7}">
		<property name="color">
			<value>Green</value>
		</property>
		<property name="name">
			<value>SFX_Player_CarCrash</value>
		</property>
		<property name="outputFormat">
			<value>1</value>
		</property>
		<relationship name="folder">
			<destination>{e1f3244a-deec-4658-b620-5dcc8aace731}</destination>
		</relationship>
		<relationship name="mixer">
			<destination>{01544d40-3a48-42a9-86a8-a7b7d17b262f}</destination>
		</relationship>
		<relationship name="masterTrack">
			<destination>{46b600c9-ef02-4e4c-a5f4-61b70ecbe88f}</destination>
		</relationship>
		<relationship name="mixerInput">
			<destination>{fe070a18-f3ab-4858-aaed-167a3e24f2d8}</destination>
		</relationship>
		<relationship name="automatableProperties">
			<destination>{12498c71-2dbb-4cdc-b0b9-ae08c2b5af57}</destination>
		</relationship>
		<relationship name="markerTracks">
			<destination>{0fc07364-63d7-4a07-90ae-8a49f108d272}</destination>
		</relationship>
		<relationship name="timeline">
			<destination>{97813560-55d6-48c7-9960-f9eb4fb84119}</destination>
		</relationship>
		<relationship name="parameters">
			<destination>{0b5a23d1-d588-418a-b713-d05110f8330a}</destination>
		</relationship>
		<relationship name="banks">
			<destination>{4251c54e-175f-418f-87f6-debbf59d6a82}</destination>
		</relationship>
	</object>
	<object class="EventMixer" id="{01544d40-3a48-42a9-86a8-a7b7d17b262f}">
		<relationship name="masterBus">
			<destination>{92a39e48-dc8d-467b-a999-f85b890e4fbe}</destination>
		</relationship>
	</object>
	<object class="MasterTrack" id="{46b600c9-ef02-4e4c-a5f4-61b70ecbe88f}">
		<relationship name="modules">
			<destination>{610c9f4f-ed85-4487-9fd1-4696c4215c27}</destination>
		</relationship>
		<relationship name="mixerGroup">
			<destination>{92a39e48-dc8d-467b-a999-f85b890e4fbe}</destination>
		</relationship>
	</object>
	<object class="MixerInput" id="{fe070a18-f3ab-4858-aaed-167a3e24f2d8}">
		<relationship name="effectChain">
			<destination>{c98e0f3a-a5ad-4482-9c48-f5358af82004}</destination>
		</relationship>
		<relationship name="panner">
			<destination>{5498de0c-077f-4a89-8a2d-89a3d959a4fd}</destination>
		</relationship>
		<relationship name="output">
			<destination>{b668158f-46c9-4d40-8906-e4fb8fc0d6f9}</destination>
		</relationship>
	</object>
	<object class="EventAutomatableProperties" id="{12498c71-2dbb-4cdc-b0b9-ae08c2b5af57}" />
	<object class="MarkerTrack" id="{0fc07364-63d7-4a07-90ae-8a49f108d272}" />
	<object class="Timeline" id="{97813560-55d6-48c7-9960-f9eb4fb84119}">
		<property name="isProxyEnabled">
			<value>false</value>
		</property>
	</object>
	<object class="ActionSheet" id="{0b5a23d1-d588-418a-b713-d05110f8330a}">
		<relationship name="modules">
			<destination>{610c9f4f-ed85-4487-9fd1-4696c4215c27}</destination>
		</relationship>
	</object>
	<object class="EventMixerMaster" id="{92a39e48-dc8d-467b-a999-f85b890e4fbe}">
		<relationship name="effectChain">
			<destination>{09941ce0-2a14-4af1-b782-0564c04f226a}</destination>
		</relationship>
		<relationship name="panner">
			<destination>{bad9b2f4-584a-4cd0-a44a-9b4a2cdc86bc}</destination>
		</relationship>
		<relationship name="mixer">
			<destination>{01544d40-3a48-42a9-86a8-a7b7d17b262f}</destination>
		</relationship>
	</object>
	<object class="MultiSound" id="{610c9f4f-ed85-4487-9fd1-4696c4215c27}">
		<relationship name="sounds">
			<destination>{9aec93a4-0564-4c7d-a225-f25e7dfdfe75}</destination>
		</relationship>
	</object>
	<object class="MixerBusEffectChain" id="{c98e0f3a-a5ad-4482-9c48-f5358af82004}">
		<relationship name="effects">
			<destination>{40dc8678-b132-4e2f-86be-2f1690ae88c5}</destination>
		</relationship>
	</object>
	<object class="MixerBusPanner" id="{5498de0c-077f-4a89-8a2d-89a3d959a4fd}" />
	<object class="MixerBusEffectChain" id="{09941ce0-2a14-4af1-b782-0564c04f226a}">
		<relationship name="effects">
			<destination>{0512c3ec-74f1-4b9d-9fc2-24f7262c8fd8}</destination>
			<destination>{78fba336-f772-4b4b-9fd6-bf54f1539744}</destination>
		</relationship>
	</object>
	<object class="MixerBusPanner" id="{bad9b2f4-584a-4cd0-a44a-9b4a2cdc86bc}" />
	<object class="SingleSound" id="{9aec93a4-0564-4c7d-a225-f25e7dfdfe75}">
		<relationship name="audioFile">
			<destination>{f8d68147-79b5-42c2-9237-1f3fc22878ba}</destination>
		</relationship>
	</object>
	<object class="MixerBusFader" id="{40dc8678-b132-4e2f-86be-2f1690ae88c5}" />
	<object class="PannerEffect" id="{0512c3ec-74f1-4b9d-9fc2-24f7262c8fd8}">
		<property name="surroundPanExtent">
			<value>0</value>
		</property>
		<property name="stereoToSurroundPanMode">
			<value>0</value>
		</property>
		<property name="surroundStereoSeparation">
			<value>0</value>
		</property>
		<property name="surroundStereoAxis">
			<value>-153.291626</value>
		</property>
		<property name="overridingOutputFormat">
			<value>1</value>
		</property>
		<relationship name="automators">
			<destination>{6e117529-f768-4bdb-b879-ac5e106e393e}</destination>
			<destination>{62c80e78-7bec-4b45-bfe8-92c3abfc4612}</destination>
			<destination>{edae1db3-f7e6-4db3-9291-733db02a1c39}</destination>
		</relationship>
	</object>
	<object class="MixerBusFader" id="{78fba336-f772-4b4b-9fd6-bf54f1539744}" />
	<object class="Automator" id="{6e117529-f768-4bdb-b879-ac5e106e393e}">
		<property name="nameOfPropertyBeingAutomated">
			<value>surroundPanDirection</value>
		</property>
		<relationship name="automationCurves">
			<destination>{bb67be67-d641-4f55-81bb-069027ac53fa}</destination>
		</relationship>
	</object>
	<object class="Automator" id="{62c80e78-7bec-4b45-bfe8-92c3abfc4612}">
		<property name="nameOfPropertyBeingAutomated">
			<value>surroundPanExtent</value>
		</property>
	</object>
	<object class="Automator" id="{edae1db3-f7e6-4db3-9291-733db02a1c39}">
		<property name="nameOfPropertyBeingAutomated">
			<value>stereoPan</value>
		</property>
		<relationship name="automationCurves">
			<destination>{24a98da2-48c5-4cb2-913a-7947264b377b}</destination>
		</relationship>
	</object>
	<object class="AutomationCurve" id="{bb67be67-d641-4f55-81bb-069027ac53fa}">
		<relationship name="parameter">
			<destination>{436bcbc2-147a-411f-b780-d9922d23f47b}</destination>
		</relationship>
		<relationship name="automationPoints">
			<destination>{7abaa2e8-7163-435d-add5-47b0a820c632}</destination>
			<destination>{4cdde8a9-a178-4c71-9524-997b6988b9f0}</destination>
		</relationship>
	</object>
	<object class="AutomationCurve" id="{24a98da2-48c5-4cb2-913a-7947264b377b}">
		<relationship name="parameter">
			<destination>{436bcbc2-147a-411f-b780-d9922d23f47b}</destination>
		</relationship>
		<relationship name="automationPoints">
			<destination>{96841514-d989-41e7-8146-a18cc6c46a5d}</destination>
			<destination>{7a2c7e00-3b26-49f1-aabb-2e5cd125d8f1}</destination>
			<destination>{6fa04e47-abf5-406c-8a8c-8f6a32991f29}</destination>
		</relationship>
	</object>
	<object class="AutomationPoint" id="{7abaa2e8-7163-435d-add5-47b0a820c632}">
		<property name="position">
			<value>-1</value>
		</property>
		<property name="value">
			<value>75.6720657</value>
		</property>
	</object>
	<object class="AutomationPoint" id="{4cdde8a9-a178-4c71-9524-997b6988b9f0}">
		<property name="position">
			<value>1</value>
		</property>
		<property name="value">
			<value>180</value>
		</property>
	</object>
	<object class="AutomationPoint" id="{96841514-d989-41e7-8146-a18cc6c46a5d}">
		<property name="position">
			<value>0</value>
		</property>
		<property name="value">
			<value>0</value>
		</property>
		<property name="curveShape">
			<value>0.00158842513</value>
		</property>
	</object>
	<object class="AutomationPoint" id="{7a2c7e00-3b26-49f1-aabb-2e5cd125d8f1}">
		<property name="position">
			<value>-1</value>
		</property>
		<property name="value">
			<value>-90</value>
		</property>
		<property name="curveShape">
			<value>0.0242554862</value>
		</property>
	</object>
	<object class="AutomationPoint" id="{6fa04e47-abf5-406c-8a8c-8f6a32991f29}">
		<property name="position">
			<value>1</value>
		</property>
		<property name="value">
			<value>90</value>
		</property>
	</object>
</objects>
